cduv/__init__.py
cduv-0.2.dist-info/METADATA
cduv-0.2.dist-info/WHEEL
cduv-0.2.dist-info/top_level.txt
cduv-0.2.dist-info/RECORD
