Metadata-Version: 2.1
Name: cduv
Version: 0.2
Summary: THis is a code
Home-page: UNKNOWN
Author: M
License: UNKNOWN
Platform: UNKNOWN
